singlecycle/memory/data_mem.v
module data_mem(
    Run,
    Clk,
    MemWr,
    Addr,
    data_input,
    data_output
);
    input                   Run;
    input                   MemWr;
    input                   Clk;
    input       [31: 0]     Addr;
    input       [31: 0]     data_input;

    output      [31: 0]     data_output;

    reg         [31: 0]     Mem     [31: 0];

    assign      data_output = Mem[Addr];

    always @(negedge Clk) begin
        if (Run == 1'b1) begin
            if (MemWr == 1'b1) begin
                Mem[Addr] <= data_input;
            end
        end
    end

    initial begin
        Mem[1] = 32'h123;
        Mem[2] = 32'h456;
        Mem[3] = 32'h789;
    end

endmodule

singlecycle/memory/testbench.v
`timescale 10ns/10ns
module testbench();
    reg                 Clk;
    reg                 Run;
    reg     [31: 0]     DataIn;
    wire    [31: 0]     DataOut;
    reg     [31: 0]     Addr;
    reg                 MemWr;

    data_mem mem1(
        .Run    (Run),
        .Clk    (Clk),
        .MemWr  (MemWr),
        .Addr   (Addr),
        .data_input     (DataIn),
        .data_output    (DataOut)
    );

    initial begin
        Clk <= 1'b1;
        MemWr <= 1'b0;
        Addr <= 0;
        DataIn <= 0;
        Run <= 1'b0;
        #10     Run <= 1'b1;
        #50     DataIn <= 32'h987;
        #50     Addr <= 5'h4;
        #50     MemWr <= 1'b1;

        #80     DataIn <= 32'h0;
        #80     Addr <= 5'h3;
        #80     MemWr <= 1'b0;

        #110    Addr <= 5'h1;
        
        #140    Addr <= 5'h2;

        #5000 $finish;
    end

    initial begin
        $dumpfile("wave.vcd");
        $dumpvars;
    end

    always begin
        #10 Clk = !Clk;
    end
endmodule

singlecycle/memory/wave.vcd
$date
	Tue Aug 24 09:59:11 2021
$end
$version
	Icarus Verilog
$end
$timescale
	10ns
$end
$scope module testbench $end
$var wire 32 ! DataOut [31:0] $end
$var reg 32 " Addr [31:0] $end
$var reg 1 # Clk $end
$var reg 32 $ DataIn [31:0] $end
$var reg 1 % MemWr $end
$var reg 1 & Run $end
$scope module mem1 $end
$var wire 32 ' Addr [31:0] $end
$var wire 1 # Clk $end
$var wire 1 % MemWr $end
$var wire 1 & Run $end
$var wire 32 ( data_input [31:0] $end
$var wire 32 ) data_output [31:0] $end
$upscope $end
$upscope $end
$enddefinitions $end
#0
$dumpvars
bx )
b0 (
b0 '
0&
0%
b0 $
1#
b0 "
bx !
$end
#10
1&
0#
#20
1#
#30
0#
#40
1#
#50
0#
#60
b100110000111 $
b100110000111 (
1#
#70
0#
#80
1#
#90
0#
#100
1#
#110
b100 "
b100 '
0#
#120
1#
#130
0#
#140
1#
#150
0#
#160
1%
1#
#170
b100110000111 !
b100110000111 )
0#
#180
1#
#190
0#
#200
1#
#210
0#
#220
1#
#230
0#
#240
b0 $
b0 (
1#
#250
b0 !
b0 )
0#
#260
1#
#270
0#
#280
1#
#290
0#
#300
1#
#310
0#
#320
b11110001001 !
b11110001001 )
b11 "
b11 '
1#
#330
b0 !
b0 )
0#
#340
1#
#350
0#
#360
1#
#370
0#
#380
1#
#390
0#
#400
0%
1#
#410
0#
#420
1#
#430
0#
#440
1#
#450
0#
#460
1#
#470
0#
#480
1#
#490
0#
#500
1#
#510
b100100011 !
b100100011 )
b1 "
b1 '
0#
#520
1#
#530
0#
#540
1#
#550
0#
#560
1#
#570
0#
#580
1#
#590
0#
#600
1#
#610
0#
#620
1#
#630
0#
#640
1#
#650
b10001010110 !
b10001010110 )
b10 "
b10 '
0#
