singlecycle/alu/alu_dispatcher.v
module alu_dispatcher(ALUctr, SUBctr, OPctr, OVctr, SIGctr);
    input   [2:0]   ALUctr;
    output          SUBctr;
    output          OVctr;
    output          SIGctr;
    output  [1:0]   OPctr;

    assign SUBctr   = ALUctr[2];
    assign OVctr    = ~ALUctr[1] & ALUctr[0];
    assign SIGctr   = ALUctr[0];
    assign OPctr[1] = ALUctr[2] & ALUctr[1];
    assign OPctr[0] = ~ALUctr[2] & ALUctr[1] & ~ALUctr[0];
endmodule

singlecycle/alu/adderk.v
module adderk (
    carryin, X, Y, 
    S, 
    carryout, AddZero, AddOverflow, AddSign
);
    parameter k = 8;
    input       [k-1:0]     X;
    input       [k-1:0]     Y;
    input                   carryin;
    output  reg [k-1:0]     S;
    output  reg             carryout;
    output  reg             AddZero;
    output  reg             AddOverflow;
    output  reg             AddSign;
    always@(X or Y or carryin)
    begin
        {carryout, S} = X + Y + carryin;
        AddZero = S == 0;
        AddOverflow = (X[k-1] & Y[k-1] & ~S[k-1]) |
                      (~X[k-1] & ~Y[k-1] & S[k-1]);
        AddSign = S[k-1];
    end
endmodule

singlecycle/alu/mux2to1.v
module mux2to1 (V, W, Selm, F);
  parameter k = 8;
  input [k-1:0] V, W;
  input Selm;
  output [k-1:0] F;
  reg [k-1:0] F;
  always @(V or W or Selm)
  if (Selm == 0) F <= V;
  else F <= W;
endmodule

singlecycle/alu/mux3to1.v
module mux3to1(U, V, W, Sel, F);
  parameter k = 8;
  input [k-1:0] U, V, W;
  input [1:0] Sel;
  output reg [k-1:0] F;
  always@(U or V or W or Sel)
  begin
    case (Sel)
      2'b00: F <= U;
      2'b01: F <= V;
      2'b10: F <= W;
    endcase
  end
endmodule

singlecycle/alu/alu.v
// `include "./alu/mux3to1.v"
// `include "./alu/mux2to1.v"
// `include "./alu/adderk.v"
// `include "./alu/alu_dispatcher.v"

module alu(
    input_a,
    input_b,
    input_aluctr,
    out_result,
    out_zero,
    out_overflow
);
    parameter n = 32;

    input   [n - 1: 0]  input_a, input_b;
    input   [    2: 0]  input_aluctr;

    output  [n - 1: 0]  out_result;
    output              out_zero, out_overflow;

    wire                Add_carry;
    wire                Add_overflow;
    wire                Add_sign;
    wire                Add_zero;
    wire    [n - 1: 0]  Add_result;
    wire                Subctr;
    wire                Ovctr;
    wire                SIGctr;
    wire                Less;
    wire    [    1: 0]  OPctr;
    wire                I;
    wire                J;
    wire    [n - 1: 0]  H;
    wire    [n - 1: 0]  G;

    assign   H          = input_b ^ {n{Subctr}};
    assign   I          = Subctr  ^ Add_carry;
    assign   J          = Add_overflow ^ Add_sign;
    assign out_overflow = Add_overflow & Ovctr;

    mux3to1 #(
        .k   (n)     //  param
    )
    multiplexer1(
        .U   (Add_result),          // input
        .V   (input_a | input_b),
        .W   (G),
        .Sel (OPctr),
        .F   (out_result)           // output
    );

    mux2to1 #(
        .k   (n)
    )
    multiplexer2(
        .V   (32'h0),
        .W   (32'h1),
        .Selm(Less),
        .F   (G)
    );

    mux2to1 #(
        .k   (1)
    )
    multiplexer3(
        .V   (I), 
        .W   (J), 
        .Selm(SIGctr), 
        .F   (Less)
    );

    adderk #(
        .k   (n)
    )
    n_adder(
        .carryin    (Subctr), 
        .X          (input_a), 
        .Y          (H), 
        .S          (Add_result), 
        .carryout   (Add_carry), 
        .AddZero    (Add_zero), 
        .AddOverflow(Add_overflow), 
        .AddSign    (Add_sign)
    );

    assign out_zero = input_aluctr == 3'b011 ? 1'b0 : Add_zero;

    alu_dispatcher d0(
        .ALUctr     (input_aluctr), 
        .SUBctr     (Subctr), 
        .OPctr      (OPctr), 
        .OVctr      (Ovctr), 
        .SIGctr     (SIGctr)
    );

endmodule

singlecycle/alu/testbench.v
`timescale 10ns/10ns

module testbench();

    initial begin
        A <= 31;
        B <= 24;
        ALUctr <= 0;
        $dumpfile("wave.vcd");
        $dumpvars;
        #5000 $finish;
    end

    reg [31:0] A, B, Result;
    reg [2:0]  ALUctr;
    wire zero, ov;

    alu #(
        .n  (32)
    )
    test_alu(
        .input_a(A),
        .input_b(B),
        .input_aluctr(ALUctr),
        .out_result(Result),
        .out_zero(zero),
        .out_overflow(ov)
    );

    always begin
        #10 ALUctr <= ALUctr + 1'b1;
    end


endmodule

singlecycle/alu/wave.vcd
$date
	Thu Aug 19 10:50:40 2021
$end
$version
	Icarus Verilog
$end
$timescale
	10ns
$end
$scope module testbench $end
$var wire 1 ! zero $end
$var wire 1 " ov $end
$var wire 32 # Result [31:0] $end
$var reg 32 $ A [31:0] $end
$var reg 3 % ALUctr [2:0] $end
$var reg 32 & B [31:0] $end
$scope module test_alu $end
$var wire 32 ' H [31:0] $end
$var wire 1 ( I $end
$var wire 1 ) J $end
$var wire 32 * input_a [31:0] $end
$var wire 3 + input_aluctr [2:0] $end
$var wire 32 , input_b [31:0] $end
$var wire 1 " out_overflow $end
$var wire 1 ! out_zero $end
$var wire 32 - out_result [31:0] $end
$var wire 1 . Subctr $end
$var wire 1 / SIGctr $end
$var wire 1 0 Ovctr $end
$var wire 2 1 OPctr [1:0] $end
$var wire 1 2 Less $end
$var wire 32 3 G [31:0] $end
$var wire 1 4 Add_zero $end
$var wire 1 5 Add_sign $end
$var wire 32 6 Add_result [31:0] $end
$var wire 1 7 Add_overflow $end
$var wire 1 8 Add_carry $end
$scope module d0 $end
$var wire 3 9 ALUctr [2:0] $end
$var wire 1 0 OVctr $end
$var wire 1 . SUBctr $end
$var wire 1 / SIGctr $end
$var wire 2 : OPctr [1:0] $end
$upscope $end
$scope module multiplexer1 $end
$var wire 2 ; Sel [1:0] $end
$var wire 32 < V [31:0] $end
$var wire 32 = W [31:0] $end
$var wire 32 > U [31:0] $end
$var reg 32 ? F [31:0] $end
$upscope $end
$scope module multiplexer2 $end
$var wire 32 @ V [31:0] $end
$var wire 32 A W [31:0] $end
$var wire 1 2 Selm $end
$var reg 32 B F [31:0] $end
$upscope $end
$scope module multiplexer3 $end
$var wire 1 / Selm $end
$var wire 1 ( V $end
$var wire 1 ) W $end
$var reg 1 2 F $end
$upscope $end
$scope module n_adder $end
$var wire 32 C X [31:0] $end
$var wire 32 D Y [31:0] $end
$var wire 1 . carryin $end
$var reg 1 7 AddOverflow $end
$var reg 1 5 AddSign $end
$var reg 1 4 AddZero $end
$var reg 32 E S [31:0] $end
$var reg 1 8 carryout $end
$upscope $end
$upscope $end
$upscope $end
$enddefinitions $end
#0
$dumpvars
b110111 E
b11000 D
b11111 C
b0 B
b1 A
b0 @
b110111 ?
b110111 >
b0 =
b11111 <
b0 ;
b0 :
b0 9
08
07
b110111 6
05
04
b0 3
02
b0 1
00
0/
0.
b110111 -
b11000 ,
b0 +
b11111 *
0)
0(
b11000 '
b11000 &
b0 %
b11111 $
b110111 #
0"
0!
$end
#10
10
1/
b1 %
b1 +
b1 9
#20
b11111 #
b11111 -
b11111 ?
b1 1
b1 :
b1 ;
00
0/
b10 %
b10 +
b10 9
#30
b110111 #
b110111 -
b110111 ?
b0 1
b0 :
b0 ;
1/
b11 %
b11 +
b11 9
#40
02
b111 #
b111 -
b111 ?
18
b11111111111111111111111111100111 '
b11111111111111111111111111100111 D
0(
b111 6
b111 >
b111 E
1.
0/
b100 %
b100 +
b100 9
#50
10
1/
b101 %
b101 +
b101 9
#60
b0 #
b0 -
b0 ?
00
b10 1
b10 :
b10 ;
0/
b110 %
b110 +
b110 9
#70
1/
b111 %
b111 +
b111 9
#80
02
b110111 #
b110111 -
b110111 ?
08
b11000 '
b11000 D
0(
b110111 6
b110111 >
b110111 E
b0 1
b0 :
b0 ;
0.
0/
b0 %
b0 +
b0 9
#90
10
1/
b1 %
b1 +
b1 9
#100
b11111 #
b11111 -
b11111 ?
b1 1
b1 :
b1 ;
00
0/
b10 %
b10 +
b10 9
#110
b110111 #
b110111 -
b110111 ?
b0 1
b0 :
b0 ;
1/
b11 %
b11 +
b11 9
#120
02
b111 #
b111 -
b111 ?
18
b11111111111111111111111111100111 '
b11111111111111111111111111100111 D
0(
b111 6
b111 >
b111 E
1.
0/
b100 %
b100 +
b100 9
#130
10
1/
b101 %
b101 +
b101 9
#140
b0 #
b0 -
b0 ?
00
b10 1
b10 :
b10 ;
0/
b110 %
b110 +
b110 9
#150
1/
b111 %
b111 +
b111 9
#160
02
b110111 #
b110111 -
b110111 ?
08
b11000 '
b11000 D
0(
b110111 6
b110111 >
b110111 E
b0 1
b0 :
b0 ;
0.
0/
b0 %
b0 +
b0 9
#170
10
1/
b1 %
b1 +
b1 9
#180
b11111 #
b11111 -
b11111 ?
b1 1
b1 :
b1 ;
00
0/
b10 %
b10 +
b10 9
#190
b110111 #
b110111 -
b110111 ?
b0 1
b0 :
b0 ;
1/
b11 %
b11 +
b11 9
#200
02
b111 #
b111 -
b111 ?
18
b11111111111111111111111111100111 '
b11111111111111111111111111100111 D
0(
b111 6
b111 >
b111 E
1.
0/
b100 %
b100 +
b100 9
#210
10
1/
b101 %
b101 +
b101 9
#220
b0 #
b0 -
b0 ?
00
b10 1
b10 :
b10 ;
0/
b110 %
b110 +
b110 9
#230
1/
b111 %
b111 +
b111 9
#240
02
b110111 #
b110111 -
b110111 ?
08
b11000 '
b11000 D
0(
b110111 6
b110111 >
b110111 E
b0 1
b0 :
b0 ;
0.
0/
b0 %
b0 +
b0 9
#250
10
1/
b1 %
b1 +
b1 9
#260
b11111 #
b11111 -
b11111 ?
b1 1
b1 :
b1 ;
00
0/
b10 %
b10 +
b10 9
#270
b110111 #
b110111 -
b110111 ?
b0 1
b0 :
b0 ;
1/
b11 %
b11 +
b11 9
#280
02
b111 #
b111 -
b111 ?
18
b11111111111111111111111111100111 '
b11111111111111111111111111100111 D
0(
b111 6
b111 >
b111 E
1.
0/
b100 %
b100 +
b100 9
#290
10
1/
b101 %
b101 +
b101 9
#300
b0 #
b0 -
b0 ?
00
b10 1
b10 :
b10 ;
0/
b110 %
b110 +
b110 9
#310
1/
b111 %
b111 +
b111 9
#320
02
b110111 #
b110111 -
b110111 ?
08
b11000 '
b11000 D
0(
b110111 6
b110111 >
b110111 E
b0 1
b0 :
b0 ;
0.
0/
b0 %
b0 +
b0 9
#330
10
1/
b1 %
b1 +
b1 9
#340
b11111 #
b11111 -
b11111 ?
b1 1
b1 :
b1 ;
00
0/
b10 %
b10 +
b10 9
#350
b110111 #
b110111 -
b110111 ?
b0 1
b0 :
b0 ;
1/
b11 %
b11 +
b11 9
#360
02
b111 #
b111 -
b111 ?
18
b11111111111111111111111111100111 '
b11111111111111111111111111100111 D
0(
b111 6
b111 >
b111 E
1.
0/
b100 %
b100 +
b100 9
#370
10
1/
b101 %
b101 +
b101 9
#380
b0 #
b0 -
b0 ?
00
b10 1
b10 :
b10 ;
0/
b110 %
b110 +
b110 9
#390
1/
b111 %
b111 +
b111 9
#400
02
b110111 #
b110111 -
b110111 ?
08
b11000 '
b11000 D
0(
b110111 6
b110111 >
b110111 E
b0 1
b0 :
b0 ;
0.
0/
b0 %
b0 +
b0 9
#410
10
1/
b1 %
b1 +
b1 9
#420
b11111 #
b11111 -
b11111 ?
b1 1
b1 :
b1 ;
00
0/
b10 %
b10 +
b10 9
#430
b110111 #
b110111 -
b110111 ?
b0 1
b0 :
b0 ;
1/
b11 %
b11 +
b11 9
#440
02
b111 #
b111 -
b111 ?
18
b11111111111111111111111111100111 '
b11111111111111111111111111100111 D
0(
b111 6
b111 >
b111 E
1.
0/
b100 %
b100 +
b100 9
#450
10
1/
b101 %
b101 +
b101 9
#460
b0 #
b0 -
b0 ?
00
b10 1
b10 :
b10 ;
0/
b110 %
b110 +
b110 9
#470
1/
b111 %
b111 +
b111 9
#480
02
b110111 #
b110111 -
b110111 ?
08
b11000 '
b11000 D
0(
b110111 6
b110111 >
b110111 E
b0 1
b0 :
b0 ;
0.
0/
b0 %
b0 +
b0 9
#490
10
1/
b1 %
b1 +
b1 9
#500
b11111 #
b11111 -
b11111 ?
b1 1
b1 :
b1 ;
00
0/
b10 %
b10 +
b10 9
#510
b110111 #
b110111 -
b110111 ?
b0 1
b0 :
b0 ;
1/
b11 %
b11 +
b11 9
#520
02
b111 #
b111 -
b111 ?
18
b11111111111111111111111111100111 '
b11111111111111111111111111100111 D
0(
b111 6
b111 >
b111 E
1.
0/
b100 %
b100 +
b100 9
#530
10
1/
b101 %
b101 +
b101 9
#540
b0 #
b0 -
b0 ?
00
b10 1
b10 :
b10 ;
0/
b110 %
b110 +
b110 9
#550
1/
b111 %
b111 +
b111 9
#560
02
b110111 #
b110111 -
b110111 ?
08
b11000 '
b11000 D
0(
b110111 6
b110111 >
b110111 E
b0 1
b0 :
b0 ;
0.
0/
b0 %
b0 +
b0 9
#570
10
1/
b1 %
b1 +
b1 9
#580
b11111 #
b11111 -
b11111 ?
b1 1
b1 :
b1 ;
00
0/
b10 %
b10 +
b10 9
#590
b110111 #
b110111 -
b110111 ?
b0 1
b0 :
b0 ;
1/
b11 %
b11 +
b11 9
#600
02
b111 #
b111 -
b111 ?
18
b11111111111111111111111111100111 '
b11111111111111111111111111100111 D
0(
b111 6
b111 >
b111 E
1.
0/
b100 %
b100 +
b100 9
#610
10
1/
b101 %
b101 +
b101 9
#620
b0 #
b0 -
b0 ?
00
b10 1
b10 :
b10 ;
0/
b110 %
b110 +
b110 9
#630
1/
b111 %
b111 +
b111 9
#640
02
b110111 #
b110111 -
b110111 ?
08
b11000 '
b11000 D
0(
b110111 6
b110111 >
b110111 E
b0 1
b0 :
b0 ;
0.
0/
b0 %
b0 +
b0 9
#650
10
1/
b1 %
b1 +
b1 9
#660
b11111 #
b11111 -
b11111 ?
b1 1
b1 :
b1 ;
00
0/
b10 %
b10 +
b10 9
#670
b110111 #
b110111 -
b110111 ?
b0 1
b0 :
b0 ;
1/
b11 %
b11 +
b11 9
#680
02
b111 #
b111 -
b111 ?
18
b11111111111111111111111111100111 '
b11111111111111111111111111100111 D
0(
b111 6
b111 >
b111 E
1.
0/
b100 %
b100 +
b100 9
#690
10
1/
b101 %
b101 +
b101 9
#700
b0 #
b0 -
b0 ?
00
b10 1
b10 :
b10 ;
0/
b110 %
b110 +
b110 9
#710
1/
b111 %
b111 +
b111 9
#720
02
b110111 #
b110111 -
b110111 ?
08
b11000 '
b11000 D
0(
b110111 6
b110111 >
b110111 E
b0 1
b0 :
b0 ;
0.
0/
b0 %
b0 +
b0 9
#730
10
1/
b1 %
b1 +
b1 9
#740
b11111 #
b11111 -
b11111 ?
b1 1
b1 :
b1 ;
00
0/
b10 %
b10 +
b10 9
#750
b110111 #
b110111 -
b110111 ?
b0 1
b0 :
b0 ;
1/
b11 %
b11 +
b11 9
#760
02
b111 #
b111 -
b111 ?
18
b11111111111111111111111111100111 '
b11111111111111111111111111100111 D
0(
b111 6
b111 >
b111 E
1.
0/
b100 %
b100 +
b100 9
#770
10
1/
b101 %
b101 +
b101 9
#780
b0 #
b0 -
b0 ?
00
b10 1
b10 :
b10 ;
0/
b110 %
b110 +
b110 9
#790
1/
b111 %
b111 +
b111 9
#800
02
b110111 #
b110111 -
b110111 ?
08
b11000 '
b11000 D
0(
b110111 6
b110111 >
b110111 E
b0 1
b0 :
b0 ;
0.
0/
b0 %
b0 +
b0 9
#810
10
1/
b1 %
b1 +
b1 9
#820
b11111 #
b11111 -
b11111 ?
b1 1
b1 :
b1 ;
00
0/
b10 %
b10 +
b10 9
#830
b110111 #
b110111 -
b110111 ?
b0 1
b0 :
b0 ;
1/
b11 %
b11 +
b11 9
#840
02
b111 #
b111 -
b111 ?
18
b11111111111111111111111111100111 '
b11111111111111111111111111100111 D
0(
b111 6
b111 >
b111 E
1.
0/
b100 %
b100 +
b100 9
#850
10
1/
b101 %
b101 +
b101 9
#860
b0 #
b0 -
b0 ?
00
b10 1
b10 :
b10 ;
0/
b110 %
b110 +
b110 9
#870
1/
b111 %
b111 +
b111 9
#880
02
b110111 #
b110111 -
b110111 ?
08
b11000 '
b11000 D
0(
b110111 6
b110111 >
b110111 E
b0 1
b0 :
b0 ;
0.
0/
b0 %
b0 +
b0 9
#890
10
1/
b1 %
b1 +
b1 9
#900
b11111 #
b11111 -
b11111 ?
b1 1
b1 :
b1 ;
00
0/
b10 %
b10 +
b10 9
#910
b110111 #
b110111 -
b110111 ?
b0 1
b0 :
b0 ;
1/
b11 %
b11 +
b11 9
#920
02
b111 #
b111 -
b111 ?
18
b11111111111111111111111111100111 '
b11111111111111111111111111100111 D
0(
b111 6
b111 >
b111 E
1.
0/
b100 %
b100 +
b100 9
#930
10
1/
b101 %
b101 +
b101 9
#940
b0 #
b0 -
b0 ?
00
b10 1
b10 :
b10 ;
0/
b110 %
b110 +
b110 9
#950
1/
b111 %
b111 +
b111 9
#960
02
b110111 #
b110111 -
b110111 ?
08
b11000 '
b11000 D
0(
b110111 6
b110111 >
b110111 E
b0 1
b0 :
b0 ;
0.
0/
b0 %
b0 +
b0 9
#970
10
1/
b1 %
b1 +
b1 9
#980
b11111 #
b11111 -
b11111 ?
b1 1
b1 :
b1 ;
00
0/
b10 %
b10 +
b10 9
#990
b110111 #
b110111 -
b110111 ?
b0 1
b0 :
b0 ;
1/
b11 %
b11 +
b11 9
#1000
02
b111 #
b111 -
b111 ?
18
b11111111111111111111111111100111 '
b11111111111111111111111111100111 D
0(
b111 6
b111 >
b111 E
1.
0/
b100 %
b100 +
b100 9
#1010
10
1/
b101 %
b101 +
b101 9
#1020
b0 #
b0 -
b0 ?
00
b10 1
b10 :
b10 ;
0/
b110 %
b110 +
b110 9
#1030
1/
b111 %
b111 +
b111 9
#1040
02
b110111 #
b110111 -
b110111 ?
08
b11000 '
b11000 D
0(
b110111 6
b110111 >
b110111 E
b0 1
b0 :
b0 ;
0.
0/
b0 %
b0 +
b0 9
#1050
10
1/
b1 %
b1 +
b1 9
#1060
b11111 #
b11111 -
b11111 ?
b1 1
b1 :
b1 ;
00
0/
b10 %
b10 +
b10 9
#1070
b110111 #
b110111 -
b110111 ?
b0 1
b0 :
b0 ;
1/
b11 %
b11 +
b11 9
#1080
02
b111 #
b111 -
b111 ?
18
b11111111111111111111111111100111 '
b11111111111111111111111111100111 D
0(
b111 6
b111 >
b111 E
1.
0/
b100 %
b100 +
b100 9
#1090
10
1/
b101 %
b101 +
b101 9
#1100
b0 #
b0 -
b0 ?
00
b10 1
b10 :
b10 ;
0/
b110 %
b110 +
b110 9
#1110
1/
b111 %
b111 +
b111 9
#1120
02
b110111 #
b110111 -
b110111 ?
08
b11000 '
b11000 D
0(
b110111 6
b110111 >
b110111 E
b0 1
b0 :
b0 ;
0.
0/
b0 %
b0 +
b0 9
#1130
10
1/
b1 %
b1 +
b1 9
#1140
b11111 #
b11111 -
b11111 ?
b1 1
b1 :
b1 ;
00
0/
b10 %
b10 +
b10 9
#1150
b110111 #
b110111 -
b110111 ?
b0 1
b0 :
b0 ;
1/
b11 %
b11 +
b11 9
#1160
02
b111 #
b111 -
b111 ?
18
b11111111111111111111111111100111 '
b11111111111111111111111111100111 D
0(
b111 6
b111 >
b111 E
1.
0/
b100 %
b100 +
b100 9
#1170
10
1/
b101 %
b101 +
b101 9
#1180
b0 #
b0 -
b0 ?
00
b10 1
b10 :
b10 ;
0/
b110 %
b110 +
b110 9
#1190
1/
b111 %
b111 +
b111 9
#1200
02
b110111 #
b110111 -
b110111 ?
08
b11000 '
b11000 D
0(
b110111 6
b110111 >
b110111 E
b0 1
b0 :
b0 ;
0.
0/
b0 %
b0 +
b0 9
#1210
10
1/
b1 %
b1 +
b1 9
#1220
b11111 #
b11111 -
b11111 ?
b1 1
b1 :
b1 ;
00
0/
b10 %
b10 +
b10 9
#1230
b110111 #
b110111 -
b110111 ?
b0 1
b0 :
b0 ;
1/
b11 %
b11 +
b11 9
#1240
02
b111 #
b111 -
b111 ?
18
b11111111111111111111111111100111 '
b11111111111111111111111111100111 D
0(
b111 6
b111 >
b111 E
1.
0/
b100 %
b100 +
b100 9
#1250
10
1/
b101 %
b101 +
b101 9
#1260
b0 #
b0 -
b0 ?
00
b10 1
b10 :
b10 ;
0/
b110 %
b110 +
b110 9
#1270
1/
b111 %
b111 +
b111 9
#1280
02
b110111 #
b110111 -
b110111 ?
08
b11000 '
b11000 D
0(
b110111 6
b110111 >
b110111 E
b0 1
b0 :
b0 ;
0.
0/
b0 %
b0 +
b0 9
#1290
10
1/
b1 %
b1 +
b1 9
#1300
b11111 #
b11111 -
b11111 ?
b1 1
b1 :
b1 ;
00
0/
b10 %
b10 +
b10 9
#1310
b110111 #
b110111 -
b110111 ?
b0 1
b0 :
b0 ;
1/
b11 %
b11 +
b11 9
#1320
02
b111 #
b111 -
b111 ?
18
b11111111111111111111111111100111 '
b11111111111111111111111111100111 D
0(
b111 6
b111 >
b111 E
1.
0/
b100 %
b100 +
b100 9
#1330
10
1/
b101 %
b101 +
b101 9
#1340
b0 #
b0 -
b0 ?
00
b10 1
b10 :
b10 ;
0/
b110 %
b110 +
b110 9
#1350
1/
b111 %
b111 +
b111 9
#1360
02
b110111 #
b110111 -
b110111 ?
08
b11000 '
b11000 D
0(
b110111 6
b110111 >
b110111 E
b0 1
b0 :
b0 ;
0.
0/
b0 %
b0 +
b0 9
#1370
10
1/
b1 %
b1 +
b1 9
#1380
b11111 #
b11111 -
b11111 ?
b1 1
b1 :
b1 ;
00
0/
b10 %
b10 +
b10 9
#1390
b110111 #
b110111 -
b110111 ?
b0 1
b0 :
b0 ;
1/
b11 %
b11 +
b11 9
#1400
02
b111 #
b111 -
b111 ?
18
b11111111111111111111111111100111 '
b11111111111111111111111111100111 D
0(
b111 6
b111 >
b111 E
1.
0/
b100 %
b100 +
b100 9
#1410
10
1/
b101 %
b101 +
b101 9
#1420
b0 #
b0 -
b0 ?
00
b10 1
b10 :
b10 ;
0/
b110 %
b110 +
b110 9
#1430
1/
b111 %
b111 +
b111 9
#1440
02
b110111 #
b110111 -
b110111 ?
08
b11000 '
b11000 D
0(
b110111 6
b110111 >
b110111 E
b0 1
b0 :
b0 ;
0.
0/
b0 %
b0 +
b0 9
#1450
10
1/
b1 %
b1 +
b1 9
#1460
b11111 #
b11111 -
b11111 ?
b1 1
b1 :
b1 ;
00
0/
b10 %
b10 +
b10 9
#1470
b110111 #
b110111 -
b110111 ?
b0 1
b0 :
b0 ;
1/
b11 %
b11 +
b11 9
#1480
02
b111 #
b111 -
b111 ?
18
b11111111111111111111111111100111 '
b11111111111111111111111111100111 D
0(
b111 6
b111 >
b111 E
1.
0/
b100 %
b100 +
b100 9
#1490
10
1/
b101 %
b101 +
b101 9
#1500
b0 #
b0 -
b0 ?
00
b10 1
b10 :
b10 ;
0/
b110 %
b110 +
b110 9
#1510
1/
b111 %
b111 +
b111 9
#1520
02
b110111 #
b110111 -
b110111 ?
08
b11000 '
b11000 D
0(
b110111 6
b110111 >
b110111 E
b0 1
b0 :
b0 ;
0.
0/
b0 %
b0 +
b0 9
#1530
10
1/
b1 %
b1 +
b1 9
#1540
b11111 #
b11111 -
b11111 ?
b1 1
b1 :
b1 ;
00
0/
b10 %
b10 +
b10 9
#1550
b110111 #
b110111 -
b110111 ?
b0 1
b0 :
b0 ;
1/
b11 %
b11 +
b11 9
#1560
02
b111 #
b111 -
b111 ?
18
b11111111111111111111111111100111 '
b11111111111111111111111111100111 D
0(
b111 6
b111 >
b111 E
1.
0/
b100 %
b100 +
b100 9
#1570
10
1/
b101 %
b101 +
b101 9
#1580
b0 #
b0 -
b0 ?
00
b10 1
b10 :
b10 ;
0/
b110 %
b110 +
b110 9
#1590
1/
b111 %
b111 +
b111 9
#1600
02
b110111 #
b110111 -
b110111 ?
08
b11000 '
b11000 D
0(
b110111 6
b110111 >
b110111 E
b0 1
b0 :
b0 ;
0.
0/
b0 %
b0 +
b0 9
#1610
10
1/
b1 %
b1 +
b1 9
#1620
b11111 #
b11111 -
b11111 ?
b1 1
b1 :
b1 ;
00
0/
b10 %
b10 +
b10 9
#1630
b110111 #
b110111 -
b110111 ?
b0 1
b0 :
b0 ;
1/
b11 %
b11 +
b11 9
#1640
02
b111 #
b111 -
b111 ?
18
b11111111111111111111111111100111 '
b11111111111111111111111111100111 D
0(
b111 6
b111 >
b111 E
1.
0/
b100 %
b100 +
b100 9
#1650
10
1/
b101 %
b101 +
b101 9
#1660
b0 #
b0 -
b0 ?
00
b10 1
b10 :
b10 ;
0/
b110 %
b110 +
b110 9
#1670
1/
b111 %
b111 +
b111 9
#1680
02
b110111 #
b110111 -
b110111 ?
08
b11000 '
b11000 D
0(
b110111 6
b110111 >
b110111 E
b0 1
b0 :
b0 ;
0.
0/
b0 %
b0 +
b0 9
#1690
10
1/
b1 %
b1 +
b1 9
#1700
b11111 #
b11111 -
b11111 ?
b1 1
b1 :
b1 ;
00
0/
b10 %
b10 +
b10 9
#1710
b110111 #
b110111 -
b110111 ?
b0 1
b0 :
b0 ;
1/
b11 %
b11 +
b11 9
#1720
02
b111 #
b111 -
b111 ?
18
b11111111111111111111111111100111 '
b11111111111111111111111111100111 D
0(
b111 6
b111 >
b111 E
1.
0/
b100 %
b100 +
b100 9
#1730
10
1/
b101 %
b101 +
b101 9
#1740
b0 #
b0 -
b0 ?
00
b10 1
b10 :
b10 ;
0/
b110 %
b110 +
b110 9
#1750
1/
b111 %
b111 +
b111 9
#1760
02
b110111 #
b110111 -
b110111 ?
08
b11000 '
b11000 D
0(
b110111 6
b110111 >
b110111 E
b0 1
b0 :
b0 ;
0.
0/
b0 %
b0 +
b0 9
#1770
10
1/
b1 %
b1 +
b1 9
#1780
b11111 #
b11111 -
b11111 ?
b1 1
b1 :
b1 ;
00
0/
b10 %
b10 +
b10 9
#1790
b110111 #
b110111 -
b110111 ?
b0 1
b0 :
b0 ;
1/
b11 %
b11 +
b11 9
#1800
02
b111 #
b111 -
b111 ?
18
b11111111111111111111111111100111 '
b11111111111111111111111111100111 D
0(
b111 6
b111 >
b111 E
1.
0/
b100 %
b100 +
b100 9
#1810
10
1/
b101 %
b101 +
b101 9
#1820
b0 #
b0 -
b0 ?
00
b10 1
b10 :
b10 ;
0/
b110 %
b110 +
b110 9
#1830
1/
b111 %
b111 +
b111 9
#1840
02
b110111 #
b110111 -
b110111 ?
08
b11000 '
b11000 D
0(
b110111 6
b110111 >
b110111 E
b0 1
b0 :
b0 ;
0.
0/
b0 %
b0 +
b0 9
#1850
10
1/
b1 %
b1 +
b1 9
#1860
b11111 #
b11111 -
b11111 ?
b1 1
b1 :
b1 ;
00
0/
b10 %
b10 +
b10 9
#1870
b110111 #
b110111 -
b110111 ?
b0 1
b0 :
b0 ;
1/
b11 %
b11 +
b11 9
#1880
02
b111 #
b111 -
b111 ?
18
b11111111111111111111111111100111 '
b11111111111111111111111111100111 D
0(
b111 6
b111 >
b111 E
1.
0/
b100 %
b100 +
b100 9
#1890
10
1/
b101 %
b101 +
b101 9
#1900
b0 #
b0 -
b0 ?
00
b10 1
b10 :
b10 ;
0/
b110 %
b110 +
b110 9
#1910
1/
b111 %
b111 +
b111 9
#1920
02
b110111 #
b110111 -
b110111 ?
08
b11000 '
b11000 D
0(
b110111 6
b110111 >
b110111 E
b0 1
b0 :
b0 ;
0.
0/
b0 %
b0 +
b0 9
#1930
10
1/
b1 %
b1 +
b1 9
#1940
b11111 #
b11111 -
b11111 ?
b1 1
b1 :
b1 ;
00
0/
b10 %
b10 +
b10 9
#1950
b110111 #
b110111 -
b110111 ?
b0 1
b0 :
b0 ;
1/
b11 %
b11 +
b11 9
#1960
02
b111 #
b111 -
b111 ?
18
b11111111111111111111111111100111 '
b11111111111111111111111111100111 D
0(
b111 6
b111 >
b111 E
1.
0/
b100 %
b100 +
b100 9
#1970
10
1/
b101 %
b101 +
b101 9
#1980
b0 #
b0 -
b0 ?
00
b10 1
b10 :
b10 ;
0/
b110 %
b110 +
b110 9
#1990
1/
b111 %
b111 +
b111 9
#2000
02
b110111 #
b110111 -
b110111 ?
08
b11000 '
b11000 D
0(
b110111 6
b110111 >
b110111 E
b0 1
b0 :
b0 ;
0.
0/
b0 %
b0 +
b0 9
#2010
10
1/
b1 %
b1 +
b1 9
#2020
b11111 #
b11111 -
b11111 ?
b1 1
b1 :
b1 ;
00
0/
b10 %
b10 +
b10 9
#2030
b110111 #
b110111 -
b110111 ?
b0 1
b0 :
b0 ;
1/
b11 %
b11 +
b11 9
#2040
02
b111 #
b111 -
b111 ?
18
b11111111111111111111111111100111 '
b11111111111111111111111111100111 D
0(
b111 6
b111 >
b111 E
1.
0/
b100 %
b100 +
b100 9
#2050
10
1/
b101 %
b101 +
b101 9
#2060
b0 #
b0 -
b0 ?
00
b10 1
b10 :
b10 ;
0/
b110 %
b110 +
b110 9
#2070
1/
b111 %
b111 +
b111 9
#2080
02
b110111 #
b110111 -
b110111 ?
08
b11000 '
b11000 D
0(
b110111 6
b110111 >
b110111 E
b0 1
b0 :
b0 ;
0.
0/
b0 %
b0 +
b0 9
#2090
10
1/
b1 %
b1 +
b1 9
#2100
b11111 #
b11111 -
b11111 ?
b1 1
b1 :
b1 ;
00
0/
b10 %
b10 +
b10 9
#2110
b110111 #
b110111 -
b110111 ?
b0 1
b0 :
b0 ;
1/
b11 %
b11 +
b11 9
#2120
02
b111 #
b111 -
b111 ?
18
b11111111111111111111111111100111 '
b11111111111111111111111111100111 D
0(
b111 6
b111 >
b111 E
1.
0/
b100 %
b100 +
b100 9
#2130
10
1/
b101 %
b101 +
b101 9
#2140
b0 #
b0 -
b0 ?
00
b10 1
b10 :
b10 ;
0/
b110 %
b110 +
b110 9
#2150
1/
b111 %
b111 +
b111 9
#2160
02
b110111 #
b110111 -
b110111 ?
08
b11000 '
b11000 D
0(
b110111 6
b110111 >
b110111 E
b0 1
b0 :
b0 ;
0.
0/
b0 %
b0 +
b0 9
