singlecycle/instruction_fetch/InstructionMem.v
module InstructionMem(addr, Instruction);
    input [31:0] addr;
    output [31:0] Instruction;
    reg [7:0] Mem [255:0];       // front means width, back means length

    assign Instruction = {Mem[3 + addr], Mem[2 + addr], Mem[1 + addr], Mem[addr]};
    initial begin
        {Mem[3],  Mem[2],  Mem[1],  Mem[0] } = {6'b100011, 5'h00, 5'h08, 16'h0};
        {Mem[7],  Mem[6],  Mem[5],  Mem[4] } = {6'h00, 5'h8, 5'h8, 5'h9, 5'h0, 6'h20};  
        {Mem[11], Mem[10], Mem[9],  Mem[8] } = {6'b100011, 5'h8, 5'ha, 16'b0};  
        {Mem[15], Mem[14], Mem[13], Mem[12]} = {6'b100011, 5'h9, 5'hb, 16'b0};
        {Mem[19], Mem[18], Mem[17], Mem[16]} = {6'b000000, 5'hb, 5'ha, 5'hb, 5'b0, 6'b100000};
        {Mem[23], Mem[22], Mem[21], Mem[20]} = {6'b101011, 5'h8, 5'hb, 16'h0};
        {Mem[27], Mem[26], Mem[25], Mem[24]} = {6'b000100, 5'hb, 5'h0, 16'h3};
        {Mem[31], Mem[30], Mem[29], Mem[28]} = {6'b000000, 5'hb, 5'ha, 5'hb, 5'b0, 6'b100010};
        {Mem[35], Mem[34], Mem[33], Mem[32]} = {6'b000000, 5'hc, 5'hb, 5'hc, 5'b0, 6'b100000};
        {Mem[39], Mem[38], Mem[37], Mem[36]} = {6'b000010, 26'h6};
        {Mem[43], Mem[42], Mem[41], Mem[40]} = {6'b101011, 5'h0, 5'hc, 16'h2};
    end
endmodule

singlecycle/alu/mux2to1.v
module mux2to1 (V, W, Selm, F);
  parameter k = 8;
  input [k-1:0] V, W;
  input Selm;
  output [k-1:0] F;
  reg [k-1:0] F;
  always @(V or W or Selm)
  if (Selm == 0) F <= V;
  else F <= W;
endmodule

singlecycle/instruction_fetch/InstructionFetch.v
// `include "./alu/mux2to1.v"
// `include "./instruction_fetch/InstructionMem.v"

module InstructionFetch
(
    Clk, Run,
    Zero, Branch, Jump,
    Instruction
);
    input Clk, Run, Branch, Jump, Zero;
    output [31:0] Instruction;
    wire [29:0] PC_1, ImmExt, PC_1_Ext, BranchResult, JumpIn, Newpc;
	reg [29:0] PC;

    assign PC_1 = PC + 30'b1;
    assign PC_1_Ext = PC_1 + ImmExt;
    assign ImmExt = {{14{Instruction[15]}}, Instruction[15:0]};
    assign JumpIn = {PC[29:26], Instruction[25:0]};

    mux2to1 #(.k(30))
    mux1 (
        .V(PC_1), 
        .W(PC_1_Ext), 
        .Selm(Branch & Zero), 
        .F(BranchResult)
    );
    mux2to1 #(.k(30))
    mux2 (
        .V(BranchResult), 
        .W(JumpIn), 
        .Selm(Jump), 
        .F(Newpc)
    );
    
    InstructionMem mem(
        .addr({PC, 2'b0}), 
        .Instruction(Instruction)
    );

    always @(negedge Clk) begin
        if (Run == 1'b1) begin
            PC <= Newpc;
        end
    end

    initial begin
        PC <= 0;
    end
endmodule

singlecycle/instruction_fetch/testbench.v
`timescale 10ns/10ns
`include "InstructionFetch.v"

module testbench();
    reg Clk;
    reg Run;
    reg Branch, Jump, Zero;
    wire [31:0] Instruction;
    InstructionFetch IF
    (
        .Clk(Clk),
        .Run(Run),
        .Zero(Zero),
        .Branch(Branch),
        .Jump(Jump),
        .Instruction(Instruction)
    );

    initial begin
        $dumpfile("wave.vcd");
        $dumpvars;
    end

    initial begin
        Clk <= 1'b0;
        Zero <= 1'b0;
        Branch <= 1'b0;
        Jump <= 1'b0;
        Run <= 1'b0;
        #10 Run <= 1'b1;
        #49 Branch <= 1; Zero <= 1;
        #21 Branch <= 0; Zero <= 0; 
        #99 Jump <= 1;
        #21 Jump <= 0;
        #500 $finish;
    end

    always begin
        #10 Clk <= !Clk;
    end

endmodule

singlecycle/instruction_fetch/wave.vcd
$date
	Sat Sep 11 16:14:03 2021
$end
$version
	Icarus Verilog
$end
$timescale
	10ns
$end
$scope module testbench $end
$var wire 32 ! Instruction [31:0] $end
$var reg 1 " Branch $end
$var reg 1 # Clk $end
$var reg 1 $ Jump $end
$var reg 1 % Run $end
$var reg 1 & Zero $end
$scope module IF $end
$var wire 1 " Branch $end
$var wire 1 # Clk $end
$var wire 1 $ Jump $end
$var wire 1 % Run $end
$var wire 1 & Zero $end
$var wire 30 ' PC_1_Ext [29:0] $end
$var wire 30 ( PC_1 [29:0] $end
$var wire 30 ) Newpc [29:0] $end
$var wire 30 * JumpIn [29:0] $end
$var wire 32 + Instruction [31:0] $end
$var wire 30 , ImmExt [29:0] $end
$var wire 30 - BranchResult [29:0] $end
$var reg 30 . PC [29:0] $end
$scope module mem $end
$var wire 32 / addr [31:0] $end
$var wire 32 0 Instruction [31:0] $end
$upscope $end
$scope module mux1 $end
$var wire 1 1 Selm $end
$var wire 30 2 V [29:0] $end
$var wire 30 3 W [29:0] $end
$var reg 30 4 F [29:0] $end
$upscope $end
$scope module mux2 $end
$var wire 1 $ Selm $end
$var wire 30 5 V [29:0] $end
$var wire 30 6 W [29:0] $end
$var reg 30 7 F [29:0] $end
$upscope $end
$upscope $end
$upscope $end
$enddefinitions $end
#0
$dumpvars
b1 7
b1111010100011000000001010 6
b1 5
b1 4
b11000000001011 3
b1 2
01
b1111010100011000000001010 0
b0 /
b0 .
b1 -
b11000000001010 ,
b1111010100011000000001010 +
b1111010100011000000001010 *
b1 )
b1 (
b11000000001011 '
0&
0%
0$
0#
0"
b1111010100011000000001010 !
$end
#10
1#
1%
#20
b10 )
b10 7
b10 -
b10 4
b10 5
b1110010110010100000000000 *
b1110010110010100000000000 6
b10100000000000 ,
b10100000000010 '
b10100000000010 3
b10 (
b10 2
b110101110010110010100000000000 !
b110101110010110010100000000000 +
b110101110010110010100000000000 0
b100 /
b1 .
0#
#30
1#
#40
b11 )
b11 7
b11 -
b11 4
b11 5
b1111000010000000000000011 *
b1111000010000000000000011 6
b11 ,
b110 '
b110 3
b11 (
b11 2
b10001111000010000000000000011 !
b10001111000010000000000000011 +
b10001111000010000000000000011 0
b1000 /
b10 .
0#
#50
1#
#59
b110 )
b110 7
b110 -
b110 4
b110 5
11
1&
1"
#60
b100001100101000 )
b100001100101000 7
b100001100101000 -
b100001100101000 4
b100001100101000 5
b11011001010100001100100001 *
b11011001010100001100100001 6
b100001100100001 ,
b100001100101000 '
b100001100101000 3
b111 (
b111 2
b10000111011001010100001100100001 !
b10000111011001010100001100100001 +
b10000111011001010100001100100001 0
b11000 /
b110 .
0#
#70
1#
#80
b100001100101001 )
b100001100101001 7
b0xxxxxxxxxxxxxxxxxxxxxxxxxx *
b0xxxxxxxxxxxxxxxxxxxxxxxxxx 6
bx ,
b100001100101001 -
b100001100101001 4
b100001100101001 5
bx '
bx 3
b100001100101001 (
b100001100101001 2
bx !
bx +
bx 0
b10000110010100000 /
b100001100101000 .
01
0#
0&
0"
#90
1#
#100
b100001100101010 )
b100001100101010 7
b100001100101010 -
b100001100101010 4
b100001100101010 5
b100001100101010 (
b100001100101010 2
b10000110010100100 /
b100001100101001 .
0#
#110
1#
#120
b100001100101011 )
b100001100101011 7
b100001100101011 -
b100001100101011 4
b100001100101011 5
b100001100101011 (
b100001100101011 2
b10000110010101000 /
b100001100101010 .
0#
#130
1#
#140
b100001100101100 )
b100001100101100 7
b100001100101100 -
b100001100101100 4
b100001100101100 5
b100001100101100 (
b100001100101100 2
b10000110010101100 /
b100001100101011 .
0#
#150
1#
#160
b100001100101101 )
b100001100101101 7
b100001100101101 -
b100001100101101 4
b100001100101101 5
b100001100101101 (
b100001100101101 2
b10000110010110000 /
b100001100101100 .
0#
#170
1#
#179
b0xxxxxxxxxxxxxxxxxxxxxxxxxx )
b0xxxxxxxxxxxxxxxxxxxxxxxxxx 7
1$
#180
bx -
bx 4
bx 5
bx (
bx 2
b0xxxxxxxxxxxxxxxxxxxxxxxxxx00 /
b0xxxxxxxxxxxxxxxxxxxxxxxxxx .
0#
#190
1#
#200
bx )
bx 7
0#
0$
#210
1#
#220
bx *
bx 6
bx00 /
bx .
0#
